MANIFEST.in
README.md
o2locktop
setup.py
o2locktop.egg-info/PKG-INFO
o2locktop.egg-info/SOURCES.txt
o2locktop.egg-info/dependency_links.txt
o2locktop.egg-info/top_level.txt
o2locktoplib/__init__.py
o2locktoplib/cat.py
o2locktoplib/config.py
o2locktoplib/dlm.py
o2locktoplib/keyboard.py
o2locktoplib/printer.py
o2locktoplib/retry.py
o2locktoplib/shell.py
o2locktoplib/util.py