Metadata-Version: 2.1
Name: o2locktop
Version: 1.0.10
Summary: o2locktop is a top-like OCFS2 DLM lock monitor
Home-page: https://github.com/ganghe/o2locktop
Author: Larry Chen, Weikai Wang, Gang He
Author-email: lchen@suse.com, wewang@suse.com, ghe@suse.com
License: GPL2.0
Platform: UNKNOWN
